am4894hubspot/__init__.py
am4894hubspot/_nbdev.py
am4894hubspot/contacts.py
am4894hubspot/core.py
am4894hubspot/search.py
am4894hubspot-0.0.14.dist-info/LICENSE
am4894hubspot-0.0.14.dist-info/METADATA
am4894hubspot-0.0.14.dist-info/WHEEL
am4894hubspot-0.0.14.dist-info/entry_points.txt
am4894hubspot-0.0.14.dist-info/top_level.txt
am4894hubspot-0.0.14.dist-info/RECORD
