Metadata-Version: 2.1
Name: am4894hubspot
Version: 0.0.14
Summary: A helper library for hubspot api
Home-page: https://github.com/andrewm4894/am4894hubspot/tree/master/
Author: Andrew Maguire
Author-email: andrewm4894@gmail.com
License: Apache Software License 2.0
Keywords: hubspot
Platform: UNKNOWN
Classifier: Development Status :: 3 - Alpha
Classifier: Intended Audience :: Developers
Classifier: License :: OSI Approved :: Apache Software License
Classifier: Natural Language :: English
Classifier: Programming Language :: Python :: 3.6
Classifier: Programming Language :: Python :: 3.7
Classifier: Programming Language :: Python :: 3.8
Requires-Python: >=3.6
Requires-Dist: python-dotenv (==0.13.0)
Requires-Dist: requests (==2.23.0)
